[
  {
    "anonymous": false,
    "inputs": [
      {
        "indexed": false,
        "internalType": "uint256",
        "name": "timeStamp",
        "type": "uint256"
      },
      {
        "indexed": false,
        "internalType": "address",
        "name": "miner",
        "type": "address"
      }
    ],
    "name": "IterationChanged",
    "type": "event"
  },
  {
    "anonymous": false,
    "inputs": [
      {
        "indexed": true,
        "internalType": "uint256",
        "name": "propsalIteration",
        "type": "uint256"
      },
      {
        "indexed": true,
        "internalType": "address",
        "name": "winner",
        "type": "address"
      },
      {
        "indexed": true,
        "internalType": "uint256",
        "name": "projectId",
        "type": "uint256"
      }
    ],
    "name": "IterationWinner",
    "type": "event"
  },
  {
    "anonymous": false,
    "inputs": [
      {
        "indexed": true,
        "internalType": "address",
        "name": "user",
        "type": "address"
      },
      {
        "indexed": false,
        "internalType": "address",
        "name": "delegatedTo",
        "type": "address"
      }
    ],
    "name": "VoteDelegated",
    "type": "event"
  },
  {
    "anonymous": false,
    "inputs": [
      {
        "indexed": true,
        "internalType": "address",
        "name": "user",
        "type": "address"
      },
      {
        "indexed": true,
        "internalType": "uint256",
        "name": "iteration",
        "type": "uint256"
      },
      {
        "indexed": true,
        "internalType": "uint256",
        "name": "proposalId",
        "type": "uint256"
      }
    ],
    "name": "VotedDirect",
    "type": "event"
  },
  {
    "anonymous": false,
    "inputs": [
      {
        "indexed": true,
        "internalType": "address",
        "name": "proxy",
        "type": "address"
      },
      {
        "indexed": false,
        "internalType": "address",
        "name": "user",
        "type": "address"
      },
      {
        "indexed": true,
        "internalType": "uint256",
        "name": "iteration",
        "type": "uint256"
      },
      {
        "indexed": true,
        "internalType": "uint256",
        "name": "proposalId",
        "type": "uint256"
      }
    ],
    "name": "VotedViaProxy",
    "type": "event"
  },
  {
    "constant": true,
    "inputs": [],
    "name": "admin",
    "outputs": [
      {
        "internalType": "address",
        "name": "",
        "type": "address"
      }
    ],
    "payable": false,
    "stateMutability": "view",
    "type": "function"
  },
  {
    "constant": true,
    "inputs": [
      {
        "internalType": "address",
        "name": "",
        "type": "address"
      }
    ],
    "name": "benefactorsProposal",
    "outputs": [
      {
        "internalType": "uint256",
        "name": "",
        "type": "uint256"
      }
    ],
    "payable": false,
    "stateMutability": "view",
    "type": "function"
  },
  {
    "constant": true,
    "inputs": [],
    "name": "depositContract",
    "outputs": [
      {
        "internalType": "contract IPoolDeposits",
        "name": "",
        "type": "address"
      }
    ],
    "payable": false,
    "stateMutability": "view",
    "type": "function"
  },
  {
    "constant": true,
    "inputs": [
      {
        "internalType": "address",
        "name": "",
        "type": "address"
      }
    ],
    "name": "iterationJoined",
    "outputs": [
      {
        "internalType": "uint256",
        "name": "",
        "type": "uint256"
      }
    ],
    "payable": false,
    "stateMutability": "view",
    "type": "function"
  },
  {
    "constant": true,
    "inputs": [],
    "name": "proposalDeadline",
    "outputs": [
      {
        "internalType": "uint256",
        "name": "",
        "type": "uint256"
      }
    ],
    "payable": false,
    "stateMutability": "view",
    "type": "function"
  },
  {
    "constant": true,
    "inputs": [
      {
        "internalType": "uint256",
        "name": "",
        "type": "uint256"
      }
    ],
    "name": "proposalDetails",
    "outputs": [
      {
        "internalType": "string",
        "name": "",
        "type": "string"
      }
    ],
    "payable": false,
    "stateMutability": "view",
    "type": "function"
  },
  {
    "constant": true,
    "inputs": [],
    "name": "proposalId",
    "outputs": [
      {
        "internalType": "uint256",
        "name": "",
        "type": "uint256"
      }
    ],
    "payable": false,
    "stateMutability": "view",
    "type": "function"
  },
  {
    "constant": true,
    "inputs": [],
    "name": "proposalIteration",
    "outputs": [
      {
        "internalType": "uint256",
        "name": "",
        "type": "uint256"
      }
    ],
    "payable": false,
    "stateMutability": "view",
    "type": "function"
  },
  {
    "constant": true,
    "inputs": [
      {
        "internalType": "uint256",
        "name": "",
        "type": "uint256"
      }
    ],
    "name": "proposalOwner",
    "outputs": [
      {
        "internalType": "address",
        "name": "",
        "type": "address"
      }
    ],
    "payable": false,
    "stateMutability": "view",
    "type": "function"
  },
  {
    "constant": true,
    "inputs": [
      {
        "internalType": "uint256",
        "name": "",
        "type": "uint256"
      },
      {
        "internalType": "uint256",
        "name": "",
        "type": "uint256"
      }
    ],
    "name": "proposalVotes",
    "outputs": [
      {
        "internalType": "uint256",
        "name": "",
        "type": "uint256"
      }
    ],
    "payable": false,
    "stateMutability": "view",
    "type": "function"
  },
  {
    "constant": true,
    "inputs": [
      {
        "internalType": "uint256",
        "name": "",
        "type": "uint256"
      }
    ],
    "name": "state",
    "outputs": [
      {
        "internalType": "enum NoLossDao_v0.ProposalState",
        "name": "",
        "type": "uint8"
      }
    ],
    "payable": false,
    "stateMutability": "view",
    "type": "function"
  },
  {
    "constant": true,
    "inputs": [
      {
        "internalType": "uint256",
        "name": "",
        "type": "uint256"
      }
    ],
    "name": "topProject",
    "outputs": [
      {
        "internalType": "uint256",
        "name": "",
        "type": "uint256"
      }
    ],
    "payable": false,
    "stateMutability": "view",
    "type": "function"
  },
  {
    "constant": true,
    "inputs": [
      {
        "internalType": "uint256",
        "name": "",
        "type": "uint256"
      },
      {
        "internalType": "address",
        "name": "",
        "type": "address"
      }
    ],
    "name": "usersNominatedProject",
    "outputs": [
      {
        "internalType": "uint256",
        "name": "",
        "type": "uint256"
      }
    ],
    "payable": false,
    "stateMutability": "view",
    "type": "function"
  },
  {
    "constant": true,
    "inputs": [
      {
        "internalType": "address",
        "name": "",
        "type": "address"
      }
    ],
    "name": "voteDelegations",
    "outputs": [
      {
        "internalType": "address",
        "name": "",
        "type": "address"
      }
    ],
    "payable": false,
    "stateMutability": "view",
    "type": "function"
  },
  {
    "constant": true,
    "inputs": [],
    "name": "votingInterval",
    "outputs": [
      {
        "internalType": "uint256",
        "name": "",
        "type": "uint256"
      }
    ],
    "payable": false,
    "stateMutability": "view",
    "type": "function"
  },
  {
    "constant": false,
    "inputs": [
      {
        "internalType": "address",
        "name": "depositContractAddress",
        "type": "address"
      },
      {
        "internalType": "uint256",
        "name": "_votingInterval",
        "type": "uint256"
      }
    ],
    "name": "initialize",
    "outputs": [],
    "payable": false,
    "stateMutability": "nonpayable",
    "type": "function"
  },
  {
    "constant": false,
    "inputs": [
      {
        "internalType": "uint256",
        "name": "newInterval",
        "type": "uint256"
      }
    ],
    "name": "changeVotingInterval",
    "outputs": [],
    "payable": false,
    "stateMutability": "nonpayable",
    "type": "function"
  },
  {
    "constant": false,
    "inputs": [
      {
        "internalType": "address",
        "name": "userAddress",
        "type": "address"
      }
    ],
    "name": "noLossDeposit",
    "outputs": [
      {
        "internalType": "bool",
        "name": "",
        "type": "bool"
      }
    ],
    "payable": false,
    "stateMutability": "nonpayable",
    "type": "function"
  },
  {
    "constant": false,
    "inputs": [
      {
        "internalType": "address",
        "name": "userAddress",
        "type": "address"
      }
    ],
    "name": "noLossWithdraw",
    "outputs": [
      {
        "internalType": "bool",
        "name": "",
        "type": "bool"
      }
    ],
    "payable": false,
    "stateMutability": "nonpayable",
    "type": "function"
  },
  {
    "constant": false,
    "inputs": [
      {
        "internalType": "string",
        "name": "proposalHash",
        "type": "string"
      },
      {
        "internalType": "address",
        "name": "benefactorAddress",
        "type": "address"
      }
    ],
    "name": "noLossCreateProposal",
    "outputs": [
      {
        "internalType": "uint256",
        "name": "newProposalId",
        "type": "uint256"
      }
    ],
    "payable": false,
    "stateMutability": "nonpayable",
    "type": "function"
  },
  {
    "constant": false,
    "inputs": [
      {
        "internalType": "address",
        "name": "benefactorAddress",
        "type": "address"
      }
    ],
    "name": "noLossWithdrawProposal",
    "outputs": [
      {
        "internalType": "bool",
        "name": "",
        "type": "bool"
      }
    ],
    "payable": false,
    "stateMutability": "nonpayable",
    "type": "function"
  },
  {
    "constant": false,
    "inputs": [
      {
        "internalType": "address",
        "name": "delegatedAddress",
        "type": "address"
      }
    ],
    "name": "delegateVoting",
    "outputs": [],
    "payable": false,
    "stateMutability": "nonpayable",
    "type": "function"
  },
  {
    "constant": false,
    "inputs": [
      {
        "internalType": "uint256",
        "name": "proposalIdToVoteFor",
        "type": "uint256"
      }
    ],
    "name": "voteDirect",
    "outputs": [],
    "payable": false,
    "stateMutability": "nonpayable",
    "type": "function"
  },
  {
    "constant": false,
    "inputs": [
      {
        "internalType": "uint256",
        "name": "proposalIdToVoteFor",
        "type": "uint256"
      },
      {
        "internalType": "address",
        "name": "delegatedFrom",
        "type": "address"
      }
    ],
    "name": "voteProxy",
    "outputs": [],
    "payable": false,
    "stateMutability": "nonpayable",
    "type": "function"
  },
  {
    "constant": false,
    "inputs": [],
    "name": "distributeFunds",
    "outputs": [],
    "payable": false,
    "stateMutability": "nonpayable",
    "type": "function"
  },
  {
    "constant": false,
    "inputs": [
      {
        "internalType": "address",
        "name": "redirectTo",
        "type": "address"
      }
    ],
    "name": "daoCareFunding",
    "outputs": [],
    "payable": false,
    "stateMutability": "nonpayable",
    "type": "function"
  }
]